{
    "contributors": null,
    "coordinates": null,
    "created_at": "Thu Oct 08 09:52:51 +0000 2015",
    "entities": {
        "hashtags": [
            {
                "indices": [
                    64,
                    69
                ],
                "text": "slow"
            },
            {
                "indices": [
                    70,
                    83
                ],
                "text": "emailinstead"
            }
        ],
        "symbols": [],
        "urls": [],
        "user_mentions": [
            {
                "id": 742552178,
                "id_str": "742552178",
                "indices": [
                    0,
                    14
                ],
                "name": "Direct Line",
                "screen_name": "DirectLine_UK"
            }
        ]
    },
    "favorite_count": 0,
    "favorited": false,
    "geo": null,
    "id": 652059069583392768,
    "id_str": "652059069583392768",
    "in_reply_to_screen_name": "DirectLine_UK",
    "in_reply_to_status_id": null,
    "in_reply_to_status_id_str": null,
    "in_reply_to_user_id": 742552178,
    "in_reply_to_user_id_str": "742552178",
    "is_quote_status": false,
    "lang": "en",
    "metadata": {
        "iso_language_code": "en",
        "result_type": "recent"
    },
    "place": null,
    "retweet_count": 0,
    "retweeted": false,
    "source": "<a href=\"http://twitter.com/download/iphone\" rel=\"nofollow\">Twitter for iPhone</a>",
    "text": "@DirectLine_UK you need to speed up the process of sending NCB. #slow #emailinstead",
    "truncated": false,
    "user": {
        "contributors_enabled": false,
        "created_at": "Mon Mar 19 13:51:14 +0000 2012",
        "default_profile": true,
        "default_profile_image": false,
        "description": "Loves Millwall, football, golf, cricket, pretty much all sport and my beautiful wife and children. Not necessarily in that order.",
        "entities": {
            "description": {
                "urls": []
            }
        },
        "favourites_count": 83,
        "follow_request_sent": false,
        "followers_count": 108,
        "following": false,
        "friends_count": 222,
        "geo_enabled": false,
        "has_extended_profile": false,
        "id": 529396931,
        "id_str": "529396931",
        "is_translation_enabled": false,
        "is_translator": false,
        "lang": "en",
        "listed_count": 3,
        "location": "",
        "name": "Rik Tyler",
        "notifications": false,
        "profile_background_color": "C0DEED",
        "profile_background_image_url": "http://abs.twimg.com/images/themes/theme1/bg.png",
        "profile_background_image_url_https": "https://abs.twimg.com/images/themes/theme1/bg.png",
        "profile_background_tile": false,
        "profile_banner_url": "https://pbs.twimg.com/profile_banners/529396931/1404489517",
        "profile_image_url": "http://pbs.twimg.com/profile_images/556498839746912256/dm_-J6SH_normal.jpeg",
        "profile_image_url_https": "https://pbs.twimg.com/profile_images/556498839746912256/dm_-J6SH_normal.jpeg",
        "profile_link_color": "0084B4",
        "profile_sidebar_border_color": "C0DEED",
        "profile_sidebar_fill_color": "DDEEF6",
        "profile_text_color": "333333",
        "profile_use_background_image": true,
        "protected": false,
        "screen_name": "R1ktyl3r",
        "statuses_count": 1299,
        "time_zone": null,
        "url": null,
        "utc_offset": null,
        "verified": false
    }
}