{
  "clicked": false,
  "_replaced_more": false,
  "archived": true,
  "num_comments": 87,
  "created": 1416036590.0,
  "saved": false,
  "selftext": "",
  "mod_reports": [],
  "secure_media_embed": {},
  "edited": false,
  "downs": 0,
  "user_reports": [],
  "link_flair_css_class": "ipad",
  "over_18": false,
  "score": 160,
  "stickied": false,
  "domain": "appleinsider.com",
  "is_self": false,
  "hidden": false,
  "_orphaned": {},
  "_api_link": "https://api.reddit.com/r/apple/comments/2md3d4/apple_inc_a8x_ipad_chip_causing_big_problems_for/?ref=search_posts",
  "link_flair_text": "iPad",
  "_comments_by_id": {},
  "visited": false,
  "thumbnail": "",
  "_has_fetched": true,
  "gilded": 0,
  "hide_score": false,
  "_info_url": "https://api.reddit.com/api/info/",
  "created_utc": 1416032990.0,
  "subreddit_id": "t5_2qh1f",
  "id": "2md3d4",
  "_params": {},
  "media_embed": {},
  "name": "t3_2md3d4",
  "quarantine": false,
  "permalink": "https://www.reddit.com/r/apple/comments/2md3d4/apple_inc_a8x_ipad_chip_causing_big_problems_for/?ref=search_posts",
  "ups": 160,
  "url": "http://appleinsider.com/articles/14/11/15/apple-inc-a8x-ipad-chip-causing-big-problems-for-intel-qualcomm-samsung-and-nvidia?utm_source=dlvr.it&utm_medium=twitter",
  "title": "Apple Inc. A8X iPad chip causing big problems for Intel, Qualcomm, Samsung and Nvidia"
}