{
    "contributors": null,
    "coordinates": {
        "coordinates": [
            -2.04020867,
            37.35832634
        ],
        "type": "Point"
    },
    "created_at": "Mon Oct 05 19:05:14 +0000 2015",
    "entities": {
        "hashtags": [],
        "symbols": [],
        "urls": [],
        "user_mentions": [
            {
                "id": 119337592,
                "id_str": "119337592",
                "indices": [
                    0,
                    8
                ],
                "name": "SSE Energy",
                "screen_name": "YourSSE"
            },
            {
                "id": 1120382208,
                "id_str": "1120382208",
                "indices": [
                    9,
                    17
                ],
                "name": "Keith Boldy",
                "screen_name": "ktboldy"
            }
        ]
    },
    "favorite_count": 1,
    "favorited": false,
    "geo": {
        "coordinates": [
            37.35832634,
            -2.04020867
        ],
        "type": "Point"
    },
    "id": 651110915723665408,
    "id_str": "651110915723665408",
    "in_reply_to_screen_name": "YourSSE",
    "in_reply_to_status_id": 650346457984204801,
    "in_reply_to_status_id_str": "650346457984204801",
    "in_reply_to_user_id": 119337592,
    "in_reply_to_user_id_str": "119337592",
    "is_quote_status": false,
    "lang": "en",
    "metadata": {
        "iso_language_code": "en",
        "result_type": "recent"
    },
    "place": {
        "attributes": {},
        "bounding_box": {
            "coordinates": [
                [
                    [
                        -2.0712934,
                        37.2878269
                    ],
                    [
                        -1.9965857,
                        37.2878269
                    ],
                    [
                        -1.9965857,
                        37.433392
                    ],
                    [
                        -2.0712934,
                        37.433392
                    ]
                ]
            ],
            "type": "Polygon"
        },
        "contained_within": [],
        "country": "Espa\u00f1a",
        "country_code": "ES",
        "full_name": "Zurgena, Andaluc\u00eda",
        "id": "d768aa10bde48f3e",
        "name": "Zurgena",
        "place_type": "city",
        "url": "https://api.twitter.com/1.1/geo/id/d768aa10bde48f3e.json"
    },
    "retweet_count": 0,
    "retweeted": false,
    "source": "<a href=\"https://twitter.com/download/android\" rel=\"nofollow\">Twitter for Android Tablets</a>",
    "text": "@YourSSE @ktboldy Really love both ads..has great atmosphere..cleverly done..and music's not so bad either...",
    "truncated": false,
    "user": {
        "contributors_enabled": false,
        "created_at": "Sun Oct 28 15:48:51 +0000 2012",
        "default_profile": true,
        "default_profile_image": false,
        "description": "Retired to Spain with my wife. Writes for the Almeria Living mag  Likes photography, cooking, travelling, reading, writing.follows West Ham!!",
        "entities": {
            "description": {
                "urls": []
            }
        },
        "favourites_count": 2164,
        "follow_request_sent": false,
        "followers_count": 249,
        "following": false,
        "friends_count": 515,
        "geo_enabled": true,
        "has_extended_profile": false,
        "id": 910568972,
        "id_str": "910568972",
        "is_translation_enabled": false,
        "is_translator": false,
        "lang": "en",
        "listed_count": 8,
        "location": "Sunny Southern Spain",
        "name": "Vic Davey",
        "notifications": false,
        "profile_background_color": "C0DEED",
        "profile_background_image_url": "http://abs.twimg.com/images/themes/theme1/bg.png",
        "profile_background_image_url_https": "https://abs.twimg.com/images/themes/theme1/bg.png",
        "profile_background_tile": false,
        "profile_banner_url": "https://pbs.twimg.com/profile_banners/910568972/1429780096",
        "profile_image_url": "http://pbs.twimg.com/profile_images/516681404873076736/vg7Jj1uX_normal.jpeg",
        "profile_image_url_https": "https://pbs.twimg.com/profile_images/516681404873076736/vg7Jj1uX_normal.jpeg",
        "profile_link_color": "0084B4",
        "profile_sidebar_border_color": "C0DEED",
        "profile_sidebar_fill_color": "DDEEF6",
        "profile_text_color": "333333",
        "profile_use_background_image": true,
        "protected": false,
        "screen_name": "VDavey3",
        "statuses_count": 4869,
        "time_zone": "Casablanca",
        "url": null,
        "utc_offset": 3600,
        "verified": false
    }
}