{
    "contributors": null,
    "coordinates": null,
    "created_at": "Tue Oct 27 00:49:44 +0000 2015",
    "entities": {
        "hashtags": [],
        "media": [
            {
                "display_url": "pic.twitter.com/JlpRPRI2CC",
                "expanded_url": "http://twitter.com/KirstynNorthrop/status/658807760524562436/photo/1",
                "id": 658807754488868864,
                "id_str": "658807754488868864",
                "indices": [
                    24,
                    47
                ],
                "media_url": "http://pbs.twimg.com/media/CSSOKYWU8AACiCx.jpg",
                "media_url_https": "https://pbs.twimg.com/media/CSSOKYWU8AACiCx.jpg",
                "sizes": {
                    "large": {
                        "h": 720,
                        "resize": "fit",
                        "w": 720
                    },
                    "medium": {
                        "h": 600,
                        "resize": "fit",
                        "w": 600
                    },
                    "small": {
                        "h": 340,
                        "resize": "fit",
                        "w": 340
                    },
                    "thumb": {
                        "h": 150,
                        "resize": "crop",
                        "w": 150
                    }
                },
                "type": "photo",
                "url": "https://t.co/JlpRPRI2CC"
            }
        ],
        "symbols": [],
        "urls": [],
        "user_mentions": [
            {
                "id": 89587925,
                "id_str": "89587925",
                "indices": [
                    0,
                    8
                ],
                "name": "Comcast",
                "screen_name": "comcast"
            }
        ]
    },
    "favorite_count": 0,
    "favorited": false,
    "geo": null,
    "id": 658807760524562436,
    "id_str": "658807760524562436",
    "in_reply_to_screen_name": "comcast",
    "in_reply_to_status_id": null,
    "in_reply_to_status_id_str": null,
    "in_reply_to_user_id": 89587925,
    "in_reply_to_user_id_str": "89587925",
    "is_quote_status": false,
    "lang": "en",
    "metadata": {
        "iso_language_code": "en",
        "result_type": "recent"
    },
    "place": null,
    "possibly_sensitive": false,
    "retweet_count": 0,
    "retweeted": false,
    "source": "<a href=\"http://twitter.com/download/android\" rel=\"nofollow\">Twitter for Android</a>",
    "text": "@comcast Please explain https://t.co/JlpRPRI2CC",
    "truncated": false,
    "user": {
        "contributors_enabled": false,
        "created_at": "Wed Nov 12 17:58:31 +0000 2014",
        "default_profile": true,
        "default_profile_image": false,
        "description": "",
        "entities": {
            "description": {
                "urls": []
            }
        },
        "favourites_count": 31,
        "follow_request_sent": false,
        "followers_count": 46,
        "following": false,
        "friends_count": 72,
        "geo_enabled": false,
        "has_extended_profile": false,
        "id": 2874031553,
        "id_str": "2874031553",
        "is_translation_enabled": false,
        "is_translator": false,
        "lang": "en",
        "listed_count": 0,
        "location": "",
        "name": "Kirstyn",
        "notifications": false,
        "profile_background_color": "C0DEED",
        "profile_background_image_url": "http://abs.twimg.com/images/themes/theme1/bg.png",
        "profile_background_image_url_https": "https://abs.twimg.com/images/themes/theme1/bg.png",
        "profile_background_tile": false,
        "profile_image_url": "http://pbs.twimg.com/profile_images/532593667174043648/CFNzgUtA_normal.jpeg",
        "profile_image_url_https": "https://pbs.twimg.com/profile_images/532593667174043648/CFNzgUtA_normal.jpeg",
        "profile_link_color": "0084B4",
        "profile_sidebar_border_color": "C0DEED",
        "profile_sidebar_fill_color": "DDEEF6",
        "profile_text_color": "333333",
        "profile_use_background_image": true,
        "protected": false,
        "screen_name": "KirstynNorthrop",
        "statuses_count": 43,
        "time_zone": null,
        "url": null,
        "utc_offset": null,
        "verified": false
    }
}