{
    "contributors": null,
    "coordinates": null,
    "created_at": "Fri Oct 23 19:20:28 +0000 2015",
    "entities": {
        "hashtags": [],
        "symbols": [],
        "urls": [],
        "user_mentions": [
            {
                "id": 1178011,
                "id_str": "1178011",
                "indices": [
                    0,
                    11
                ],
                "name": "Wells Fargo",
                "screen_name": "WellsFargo"
            }
        ]
    },
    "favorite_count": 0,
    "favorited": false,
    "geo": null,
    "id": 657637732085186560,
    "id_str": "657637732085186560",
    "in_reply_to_screen_name": "WellsFargo",
    "in_reply_to_status_id": null,
    "in_reply_to_status_id_str": null,
    "in_reply_to_user_id": 1178011,
    "in_reply_to_user_id_str": "1178011",
    "is_quote_status": false,
    "lang": "en",
    "metadata": {
        "iso_language_code": "en",
        "result_type": "recent"
    },
    "place": {
        "attributes": {},
        "bounding_box": {
            "coordinates": [
                [
                    [
                        -117.399853,
                        33.152639
                    ],
                    [
                        -117.241905,
                        33.152639
                    ],
                    [
                        -117.241905,
                        33.299993
                    ],
                    [
                        -117.399853,
                        33.299993
                    ]
                ]
            ],
            "type": "Polygon"
        },
        "contained_within": [],
        "country": "United States",
        "country_code": "US",
        "full_name": "Oceanside, CA",
        "id": "1cf657005480e70e",
        "name": "Oceanside",
        "place_type": "city",
        "url": "https://api.twitter.com/1.1/geo/id/1cf657005480e70e.json"
    },
    "retweet_count": 0,
    "retweeted": false,
    "source": "<a href=\"http://twitter.com/download/iphone\" rel=\"nofollow\">Twitter for iPhone</a>",
    "text": "@WellsFargo Great Job preventing online fraud.",
    "truncated": false,
    "user": {
        "contributors_enabled": false,
        "created_at": "Sun Jan 11 21:32:19 +0000 2015",
        "default_profile": true,
        "default_profile_image": false,
        "description": "",
        "entities": {
            "description": {
                "urls": []
            }
        },
        "favourites_count": 960,
        "follow_request_sent": false,
        "followers_count": 12,
        "following": false,
        "friends_count": 14,
        "geo_enabled": true,
        "has_extended_profile": true,
        "id": 2973721354,
        "id_str": "2973721354",
        "is_translation_enabled": false,
        "is_translator": false,
        "lang": "en",
        "listed_count": 0,
        "location": "",
        "name": "Enrique Limon",
        "notifications": false,
        "profile_background_color": "C0DEED",
        "profile_background_image_url": "http://abs.twimg.com/images/themes/theme1/bg.png",
        "profile_background_image_url_https": "https://abs.twimg.com/images/themes/theme1/bg.png",
        "profile_background_tile": false,
        "profile_banner_url": "https://pbs.twimg.com/profile_banners/2973721354/1432096722",
        "profile_image_url": "http://pbs.twimg.com/profile_images/600883218141720577/lKLQSyfV_normal.jpg",
        "profile_image_url_https": "https://pbs.twimg.com/profile_images/600883218141720577/lKLQSyfV_normal.jpg",
        "profile_link_color": "0084B4",
        "profile_sidebar_border_color": "C0DEED",
        "profile_sidebar_fill_color": "DDEEF6",
        "profile_text_color": "333333",
        "profile_use_background_image": true,
        "protected": false,
        "screen_name": "EnriqueLimon619",
        "statuses_count": 186,
        "time_zone": null,
        "url": null,
        "utc_offset": null,
        "verified": false
    }
}