{
    "contributors": null,
    "coordinates": null,
    "created_at": "Fri Apr 22 19:11:19 +0000 2016",
    "entities": {
        "hashtags": [],
        "symbols": [],
        "urls": [
            {
                "display_url": "twitter.com/gonaguirrem/st\u2026",
                "expanded_url": "https://twitter.com/gonaguirrem/status/723589415059202048",
                "indices": [
                    117,
                    140
                ],
                "url": "https://t.co/rFORrkWDSL"
            }
        ],
        "user_mentions": [
            {
                "id": 2425151,
                "id_str": "2425151",
                "indices": [
                    0,
                    9
                ],
                "name": "Facebook",
                "screen_name": "facebook"
            }
        ]
    },
    "favorite_count": 0,
    "favorited": false,
    "geo": null,
    "id": 723590021824024576,
    "id_str": "723590021824024576",
    "in_reply_to_screen_name": "facebook",
    "in_reply_to_status_id": null,
    "in_reply_to_status_id_str": null,
    "in_reply_to_user_id": 2425151,
    "in_reply_to_user_id_str": "2425151",
    "is_quote_status": true,
    "lang": "en",
    "metadata": {
        "iso_language_code": "en",
        "result_type": "recent"
    },
    "place": null,
    "possibly_sensitive": false,
    "quoted_status": {
        "contributors": null,
        "coordinates": null,
        "created_at": "Fri Apr 22 19:08:54 +0000 2016",
        "entities": {
            "hashtags": [],
            "media": [
                {
                    "display_url": "pic.twitter.com/De14CaeShI",
                    "expanded_url": "http://twitter.com/gonaguirrem/status/723589415059202048/photo/1",
                    "id": 723589394628747265,
                    "id_str": "723589394628747265",
                    "indices": [
                        36,
                        59
                    ],
                    "media_url": "http://pbs.twimg.com/media/Cgq0uH4WIAEi8VA.jpg",
                    "media_url_https": "https://pbs.twimg.com/media/Cgq0uH4WIAEi8VA.jpg",
                    "sizes": {
                        "large": {
                            "h": 1820,
                            "resize": "fit",
                            "w": 1024
                        },
                        "medium": {
                            "h": 1067,
                            "resize": "fit",
                            "w": 600
                        },
                        "small": {
                            "h": 604,
                            "resize": "fit",
                            "w": 340
                        },
                        "thumb": {
                            "h": 150,
                            "resize": "crop",
                            "w": 150
                        }
                    },
                    "type": "photo",
                    "url": "https://t.co/De14CaeShI"
                }
            ],
            "symbols": [],
            "urls": [],
            "user_mentions": [
                {
                    "id": 491378686,
                    "id_str": "491378686",
                    "indices": [
                        0,
                        12
                    ],
                    "name": "Steph Kegels",
                    "screen_name": "Stephkegels"
                }
            ]
        },
        "favorite_count": 0,
        "favorited": false,
        "geo": null,
        "id": 723589415059202048,
        "id_str": "723589415059202048",
        "in_reply_to_screen_name": "Stephkegels",
        "in_reply_to_status_id": null,
        "in_reply_to_status_id_str": null,
        "in_reply_to_user_id": 491378686,
        "in_reply_to_user_id_str": "491378686",
        "is_quote_status": false,
        "lang": "en",
        "metadata": {
            "iso_language_code": "en",
            "result_type": "recent"
        },
        "place": null,
        "possibly_sensitive": false,
        "retweet_count": 0,
        "retweeted": false,
        "source": "<a href=\"http://twitter.com/download/android\" rel=\"nofollow\">Twitter for Android</a>",
        "text": "@Stephkegels i found your evil twin https://t.co/De14CaeShI",
        "truncated": false,
        "user": {
            "contributors_enabled": false,
            "created_at": "Mon Dec 22 18:39:48 +0000 2014",
            "default_profile": true,
            "default_profile_image": false,
            "description": "",
            "entities": {
                "description": {
                    "urls": []
                }
            },
            "favourites_count": 391,
            "follow_request_sent": false,
            "followers_count": 48,
            "following": false,
            "friends_count": 161,
            "geo_enabled": true,
            "has_extended_profile": false,
            "id": 2937308705,
            "id_str": "2937308705",
            "is_translation_enabled": false,
            "is_translator": false,
            "lang": "es",
            "listed_count": 0,
            "location": "",
            "name": "Gonzalo Aguirre",
            "notifications": false,
            "profile_background_color": "C0DEED",
            "profile_background_image_url": "http://abs.twimg.com/images/themes/theme1/bg.png",
            "profile_background_image_url_https": "https://abs.twimg.com/images/themes/theme1/bg.png",
            "profile_background_tile": false,
            "profile_banner_url": "https://pbs.twimg.com/profile_banners/2937308705/1452041097",
            "profile_image_url": "http://pbs.twimg.com/profile_images/684536097037258753/wRtBe16p_normal.jpg",
            "profile_image_url_https": "https://pbs.twimg.com/profile_images/684536097037258753/wRtBe16p_normal.jpg",
            "profile_link_color": "0084B4",
            "profile_sidebar_border_color": "C0DEED",
            "profile_sidebar_fill_color": "DDEEF6",
            "profile_text_color": "333333",
            "profile_use_background_image": true,
            "protected": false,
            "screen_name": "gonaguirrem",
            "statuses_count": 663,
            "time_zone": null,
            "url": null,
            "utc_offset": null,
            "verified": false
        }
    },
    "quoted_status_id": 723589415059202048,
    "quoted_status_id_str": "723589415059202048",
    "retweet_count": 0,
    "retweeted": false,
    "source": "<a href=\"http://twitter.com/download/iphone\" rel=\"nofollow\">Twitter for iPhone</a>",
    "text": "@facebook this person is using my pics and asking people to send her money through western union. Please delete her. https://t.co/rFORrkWDSL",
    "truncated": false,
    "user": {
        "contributors_enabled": false,
        "created_at": "Mon Feb 13 15:32:46 +0000 2012",
        "default_profile": false,
        "default_profile_image": false,
        "description": "Dominican. Crazy cat lady. This, cam, && IG (@KegelMaister) Buy me ish: https://t.co/DmBqCfEVpu",
        "entities": {
            "description": {
                "urls": [
                    {
                        "display_url": "amzn.com/w/238NME4B8RVHD",
                        "expanded_url": "http://amzn.com/w/238NME4B8RVHD",
                        "indices": [
                            72,
                            95
                        ],
                        "url": "https://t.co/DmBqCfEVpu"
                    }
                ]
            },
            "url": {
                "urls": [
                    {
                        "display_url": "new.naked.com/webcam/Steph-K\u2026",
                        "expanded_url": "http://new.naked.com/webcam/Steph-Kegels/21838",
                        "indices": [
                            0,
                            23
                        ],
                        "url": "https://t.co/eL8LMOghs2"
                    }
                ]
            }
        },
        "favourites_count": 3353,
        "follow_request_sent": false,
        "followers_count": 59873,
        "following": false,
        "friends_count": 201,
        "geo_enabled": false,
        "has_extended_profile": true,
        "id": 491378686,
        "id_str": "491378686",
        "is_translation_enabled": false,
        "is_translator": false,
        "lang": "en",
        "listed_count": 239,
        "location": "Miami, FL",
        "name": "Steph Kegels",
        "notifications": false,
        "profile_background_color": "000000",
        "profile_background_image_url": "http://abs.twimg.com/images/themes/theme1/bg.png",
        "profile_background_image_url_https": "https://abs.twimg.com/images/themes/theme1/bg.png",
        "profile_background_tile": false,
        "profile_banner_url": "https://pbs.twimg.com/profile_banners/491378686/1397854055",
        "profile_image_url": "http://pbs.twimg.com/profile_images/714994619038240771/_vmr8EO9_normal.jpg",
        "profile_image_url_https": "https://pbs.twimg.com/profile_images/714994619038240771/_vmr8EO9_normal.jpg",
        "profile_link_color": "9266CC",
        "profile_sidebar_border_color": "000000",
        "profile_sidebar_fill_color": "000000",
        "profile_text_color": "000000",
        "profile_use_background_image": false,
        "protected": false,
        "screen_name": "Stephkegels",
        "statuses_count": 13806,
        "time_zone": "Atlantic Time (Canada)",
        "url": "https://t.co/eL8LMOghs2",
        "utc_offset": -10800,
        "verified": false
    }
}