{
    "contributors": null,
    "coordinates": null,
    "created_at": "Wed Jun 08 22:56:43 +0000 2016",
    "entities": {
        "hashtags": [],
        "symbols": [],
        "urls": [],
        "user_mentions": [
            {
                "id": 2425151,
                "id_str": "2425151",
                "indices": [
                    0,
                    9
                ],
                "name": "Facebook",
                "screen_name": "facebook"
            }
        ]
    },
    "favorite_count": 1,
    "favorited": false,
    "geo": null,
    "id": 740678973538107392,
    "id_str": "740678973538107392",
    "in_reply_to_screen_name": "facebook",
    "in_reply_to_status_id": null,
    "in_reply_to_status_id_str": null,
    "in_reply_to_user_id": 2425151,
    "in_reply_to_user_id_str": "2425151",
    "is_quote_status": false,
    "lang": "en",
    "metadata": {
        "iso_language_code": "en",
        "result_type": "recent"
    },
    "place": {
        "attributes": {},
        "bounding_box": {
            "coordinates": [
                [
                    [
                        -1.37637,
                        54.8217178
                    ],
                    [
                        -1.319712,
                        54.8217178
                    ],
                    [
                        -1.319712,
                        54.853863
                    ],
                    [
                        -1.37637,
                        54.853863
                    ]
                ]
            ],
            "type": "Polygon"
        },
        "contained_within": [],
        "country": "United Kingdom",
        "country_code": "GB",
        "full_name": "Seaham, England",
        "id": "7f91f4c2883c247b",
        "name": "Seaham",
        "place_type": "city",
        "url": "https://api.twitter.com/1.1/geo/id/7f91f4c2883c247b.json"
    },
    "retweet_count": 3,
    "retweeted": false,
    "source": "<a href=\"http://twitter.com/download/iphone\" rel=\"nofollow\">Twitter for iPhone</a>",
    "text": "@facebook WHY HAS MESSENGER DELETED ALL MY CHATS AND NOT LOADING ANYTHING",
    "truncated": false,
    "user": {
        "contributors_enabled": false,
        "created_at": "Sun Jun 27 19:14:01 +0000 2010",
        "default_profile": false,
        "default_profile_image": false,
        "description": "Caitlin sing is a song",
        "entities": {
            "description": {
                "urls": []
            }
        },
        "favourites_count": 10599,
        "follow_request_sent": false,
        "followers_count": 2142,
        "following": false,
        "friends_count": 2726,
        "geo_enabled": true,
        "has_extended_profile": false,
        "id": 160287280,
        "id_str": "160287280",
        "is_translation_enabled": false,
        "is_translator": false,
        "lang": "en",
        "listed_count": 12,
        "location": "North East, England",
        "name": "meg",
        "notifications": false,
        "profile_background_color": "C0DEED",
        "profile_background_image_url": "http://pbs.twimg.com/profile_background_images/673620238/4849092f6b9af1769fe2920fcca73d97.jpeg",
        "profile_background_image_url_https": "https://pbs.twimg.com/profile_background_images/673620238/4849092f6b9af1769fe2920fcca73d97.jpeg",
        "profile_background_tile": true,
        "profile_banner_url": "https://pbs.twimg.com/profile_banners/160287280/1462720403",
        "profile_image_url": "http://pbs.twimg.com/profile_images/739622583457488896/vmmYF9PI_normal.jpg",
        "profile_image_url_https": "https://pbs.twimg.com/profile_images/739622583457488896/vmmYF9PI_normal.jpg",
        "profile_link_color": "F5ABB5",
        "profile_sidebar_border_color": "FFFFFF",
        "profile_sidebar_fill_color": "DDEEF6",
        "profile_text_color": "333333",
        "profile_use_background_image": true,
        "protected": false,
        "screen_name": "Megan_charltonx",
        "statuses_count": 53807,
        "time_zone": null,
        "url": null,
        "utc_offset": null,
        "verified": false
    }
}