{
    "contributors": null,
    "coordinates": null,
    "created_at": "Wed Jun 22 14:19:08 +0000 2016",
    "entities": {
        "hashtags": [
            {
                "indices": [
                    72,
                    79
                ],
                "text": "SHRM16"
            },
            {
                "indices": [
                    80,
                    87
                ],
                "text": "useful"
            },
            {
                "indices": [
                    88,
                    98
                ],
                "text": "looksgood"
            }
        ],
        "symbols": [],
        "urls": [],
        "user_mentions": [
            {
                "id": 15637008,
                "id_str": "15637008",
                "indices": [
                    0,
                    11
                ],
                "name": "Nationwide",
                "screen_name": "Nationwide"
            }
        ]
    },
    "favorite_count": 0,
    "favorited": false,
    "geo": null,
    "id": 745622151571480576,
    "id_str": "745622151571480576",
    "in_reply_to_screen_name": "Nationwide",
    "in_reply_to_status_id": null,
    "in_reply_to_status_id_str": null,
    "in_reply_to_user_id": 15637008,
    "in_reply_to_user_id_str": "15637008",
    "is_quote_status": false,
    "lang": "en",
    "metadata": {
        "iso_language_code": "en",
        "result_type": "recent"
    },
    "place": null,
    "retweet_count": 0,
    "retweeted": false,
    "source": "<a href=\"http://twitter.com/download/android\" rel=\"nofollow\">Twitter for Android</a>",
    "text": "@Nationwide thank you for this year's bags! Finally a bag with purpose! #SHRM16 #useful #looksgood",
    "truncated": false,
    "user": {
        "contributors_enabled": false,
        "created_at": "Fri Apr 17 13:43:22 +0000 2009",
        "default_profile": false,
        "default_profile_image": false,
        "description": "Corporate Compliance Director. Strategic HR professional passionate about people, policies and positivity! SMAHRA (Southern MN Area HR Association ) President.",
        "entities": {
            "description": {
                "urls": []
            }
        },
        "favourites_count": 257,
        "follow_request_sent": false,
        "followers_count": 114,
        "following": false,
        "friends_count": 193,
        "geo_enabled": true,
        "has_extended_profile": false,
        "id": 32408491,
        "id_str": "32408491",
        "is_translation_enabled": false,
        "is_translator": false,
        "lang": "en",
        "listed_count": 18,
        "location": "Mankato MN",
        "name": "Christina James",
        "notifications": false,
        "profile_background_color": "000000",
        "profile_background_image_url": "http://abs.twimg.com/images/themes/theme5/bg.gif",
        "profile_background_image_url_https": "https://abs.twimg.com/images/themes/theme5/bg.gif",
        "profile_background_tile": false,
        "profile_banner_url": "https://pbs.twimg.com/profile_banners/32408491/1440085416",
        "profile_image_url": "http://pbs.twimg.com/profile_images/502280536195207169/G8k8LcjL_normal.jpeg",
        "profile_image_url_https": "https://pbs.twimg.com/profile_images/502280536195207169/G8k8LcjL_normal.jpeg",
        "profile_link_color": "F5ABB5",
        "profile_sidebar_border_color": "000000",
        "profile_sidebar_fill_color": "000000",
        "profile_text_color": "000000",
        "profile_use_background_image": false,
        "protected": false,
        "screen_name": "iowa17",
        "statuses_count": 450,
        "time_zone": "Pacific Time (US & Canada)",
        "url": null,
        "utc_offset": -25200,
        "verified": false
    }
}