{
    "contributors": null,
    "coordinates": null,
    "created_at": "Fri Oct 23 10:32:22 +0000 2015",
    "entities": {
        "hashtags": [
            {
                "indices": [
                    107,
                    116
                ],
                "text": "IMACELEB"
            }
        ],
        "symbols": [],
        "urls": [
            {
                "display_url": "amp.twimg.com/v/f9c58ad9-0b2\u2026",
                "expanded_url": "https://amp.twimg.com/v/f9c58ad9-0b2f-48bb-8cc9-a5c6438f3952",
                "indices": [
                    117,
                    140
                ],
                "url": "https://t.co/j9SLiPBtKv"
            }
        ],
        "user_mentions": [
            {
                "id": 17386885,
                "id_str": "17386885",
                "indices": [
                    28,
                    38
                ],
                "name": "antanddec",
                "screen_name": "antanddec"
            },
            {
                "id": 17310915,
                "id_str": "17310915",
                "indices": [
                    62,
                    75
                ],
                "name": "imacelebrity",
                "screen_name": "imacelebrity"
            }
        ]
    },
    "favorite_count": 71,
    "favorited": false,
    "geo": null,
    "id": 657504832589205504,
    "id_str": "657504832589205504",
    "in_reply_to_screen_name": null,
    "in_reply_to_status_id": null,
    "in_reply_to_status_id_str": null,
    "in_reply_to_user_id": null,
    "in_reply_to_user_id_str": null,
    "is_quote_status": false,
    "lang": "en",
    "metadata": {
        "iso_language_code": "en",
        "result_type": "recent"
    },
    "place": null,
    "possibly_sensitive": false,
    "retweet_count": 109,
    "retweeted": false,
    "source": "<a href=\"http://twitter.com\" rel=\"nofollow\">Twitter Web Client</a>",
    "text": "So many people want to help @antanddec we may release the new @imacelebrity promo REALLY soon. RT THIS NOW\n#IMACELEB\nhttps://t.co/j9SLiPBtKv",
    "truncated": false,
    "user": {
        "contributors_enabled": false,
        "created_at": "Mon Nov 02 11:43:31 +0000 2009",
        "default_profile": false,
        "default_profile_image": false,
        "description": "The official Twitter home of ITV. Please note that tweets to @ITV may be displayed on online and on air by ITV. Full interactive terms at http://t.co/ligcxZ9Okv",
        "entities": {
            "description": {
                "urls": [
                    {
                        "display_url": "bit.ly/1Ffw22K",
                        "expanded_url": "http://bit.ly/1Ffw22K",
                        "indices": [
                            138,
                            160
                        ],
                        "url": "http://t.co/ligcxZ9Okv"
                    }
                ]
            },
            "url": {
                "urls": [
                    {
                        "display_url": "itv.com/itv",
                        "expanded_url": "http://www.itv.com/itv",
                        "indices": [
                            0,
                            22
                        ],
                        "url": "http://t.co/yVqyjVy5X0"
                    }
                ]
            }
        },
        "favourites_count": 1040,
        "follow_request_sent": false,
        "followers_count": 1264375,
        "following": false,
        "friends_count": 3767,
        "geo_enabled": false,
        "has_extended_profile": false,
        "id": 86925202,
        "id_str": "86925202",
        "is_translation_enabled": false,
        "is_translator": false,
        "lang": "en",
        "listed_count": 1309,
        "location": "ITV Towers",
        "name": "ITV",
        "notifications": false,
        "profile_background_color": "000000",
        "profile_background_image_url": "http://pbs.twimg.com/profile_background_images/447284550696062976/CKcjNTIk.png",
        "profile_background_image_url_https": "https://pbs.twimg.com/profile_background_images/447284550696062976/CKcjNTIk.png",
        "profile_background_tile": false,
        "profile_banner_url": "https://pbs.twimg.com/profile_banners/86925202/1445443158",
        "profile_image_url": "http://pbs.twimg.com/profile_images/508354570951483392/DBIWbMwO_normal.jpeg",
        "profile_image_url_https": "https://pbs.twimg.com/profile_images/508354570951483392/DBIWbMwO_normal.jpeg",
        "profile_link_color": "038543",
        "profile_sidebar_border_color": "FFFFFF",
        "profile_sidebar_fill_color": "FFFFFF",
        "profile_text_color": "282828",
        "profile_use_background_image": true,
        "protected": false,
        "screen_name": "ITV",
        "statuses_count": 32638,
        "time_zone": "London",
        "url": "http://t.co/yVqyjVy5X0",
        "utc_offset": 3600,
        "verified": true
    }
}