{
    "contributors": null,
    "coordinates": null,
    "created_at": "Mon Oct 26 21:55:23 +0000 2015",
    "entities": {
        "hashtags": [
            {
                "indices": [
                    61,
                    71
                ],
                "text": "Money2020"
            }
        ],
        "symbols": [],
        "urls": [
            {
                "display_url": "amp.twimg.com/v/04cdffee-0ba\u2026",
                "expanded_url": "https://amp.twimg.com/v/04cdffee-0bad-4d48-8da3-df6788915012",
                "indices": [
                    72,
                    95
                ],
                "url": "https://t.co/RBNbOFbxYY"
            }
        ],
        "user_mentions": [
            {
                "id": 274673392,
                "id_str": "274673392",
                "indices": [
                    3,
                    9
                ],
                "name": "Chase",
                "screen_name": "Chase"
            }
        ]
    },
    "favorite_count": 0,
    "favorited": false,
    "geo": null,
    "id": 658763883025448961,
    "id_str": "658763883025448961",
    "in_reply_to_screen_name": null,
    "in_reply_to_status_id": null,
    "in_reply_to_status_id_str": null,
    "in_reply_to_user_id": null,
    "in_reply_to_user_id_str": null,
    "is_quote_status": false,
    "lang": "en",
    "metadata": {
        "iso_language_code": "en",
        "result_type": "recent"
    },
    "place": null,
    "possibly_sensitive": false,
    "retweet_count": 36,
    "retweeted": false,
    "retweeted_status": {
        "contributors": null,
        "coordinates": null,
        "created_at": "Mon Oct 26 21:01:55 +0000 2015",
        "entities": {
            "hashtags": [
                {
                    "indices": [
                        50,
                        60
                    ],
                    "text": "Money2020"
                }
            ],
            "symbols": [],
            "urls": [
                {
                    "display_url": "amp.twimg.com/v/04cdffee-0ba\u2026",
                    "expanded_url": "https://amp.twimg.com/v/04cdffee-0bad-4d48-8da3-df6788915012",
                    "indices": [
                        61,
                        84
                    ],
                    "url": "https://t.co/RBNbOFbxYY"
                }
            ],
            "user_mentions": []
        },
        "favorite_count": 32,
        "favorited": false,
        "geo": null,
        "id": 658750426896953345,
        "id_str": "658750426896953345",
        "in_reply_to_screen_name": null,
        "in_reply_to_status_id": null,
        "in_reply_to_status_id_str": null,
        "in_reply_to_user_id": null,
        "in_reply_to_user_id_str": null,
        "is_quote_status": false,
        "lang": "en",
        "metadata": {
            "iso_language_code": "en",
            "result_type": "recent"
        },
        "place": null,
        "possibly_sensitive": false,
        "retweet_count": 36,
        "retweeted": false,
        "source": "<a href=\"http://twitter.com\" rel=\"nofollow\">Twitter Web Client</a>",
        "text": "Simple. Rewarding. Secure. Introducing Chase Pay. #Money2020\nhttps://t.co/RBNbOFbxYY",
        "truncated": false,
        "user": {
            "contributors_enabled": false,
            "created_at": "Wed Mar 30 20:40:17 +0000 2011",
            "default_profile": false,
            "default_profile_image": false,
            "description": "Official handle for Chase, managed by Mere (^MK), Jess (^JS) and Jaclyn (^JD). For customer support: @ChaseSupport. http://t.co/co5RnmqJXe",
            "entities": {
                "description": {
                    "urls": [
                        {
                            "display_url": "bit.ly/ChaseTermsCond\u2026",
                            "expanded_url": "http://bit.ly/ChaseTermsConditions",
                            "indices": [
                                116,
                                138
                            ],
                            "url": "http://t.co/co5RnmqJXe"
                        }
                    ]
                },
                "url": {
                    "urls": [
                        {
                            "display_url": "chase.com",
                            "expanded_url": "https://www.chase.com",
                            "indices": [
                                0,
                                23
                            ],
                            "url": "https://t.co/F819Vgwj27"
                        }
                    ]
                }
            },
            "favourites_count": 18022,
            "follow_request_sent": false,
            "followers_count": 301751,
            "following": false,
            "friends_count": 4745,
            "geo_enabled": true,
            "has_extended_profile": false,
            "id": 274673392,
            "id_str": "274673392",
            "is_translation_enabled": false,
            "is_translator": false,
            "lang": "en",
            "listed_count": 866,
            "location": "New York, NY",
            "name": "Chase",
            "notifications": false,
            "profile_background_color": "ABB8C2",
            "profile_background_image_url": "http://pbs.twimg.com/profile_background_images/378800000062685378/6c3f4eb3d41990df0764c54dbd728f7d.jpeg",
            "profile_background_image_url_https": "https://pbs.twimg.com/profile_background_images/378800000062685378/6c3f4eb3d41990df0764c54dbd728f7d.jpeg",
            "profile_background_tile": false,
            "profile_banner_url": "https://pbs.twimg.com/profile_banners/274673392/1445893316",
            "profile_image_url": "http://pbs.twimg.com/profile_images/501888576863219712/K5FabgR4_normal.png",
            "profile_image_url_https": "https://pbs.twimg.com/profile_images/501888576863219712/K5FabgR4_normal.png",
            "profile_link_color": "0F5BA7",
            "profile_sidebar_border_color": "FFFFFF",
            "profile_sidebar_fill_color": "DDEEF6",
            "profile_text_color": "333333",
            "profile_use_background_image": false,
            "protected": false,
            "screen_name": "Chase",
            "statuses_count": 18745,
            "time_zone": "Eastern Time (US & Canada)",
            "url": "https://t.co/F819Vgwj27",
            "utc_offset": -14400,
            "verified": true
        }
    },
    "source": "<a href=\"http://twitter.com\" rel=\"nofollow\">Twitter Web Client</a>",
    "text": "RT @Chase: Simple. Rewarding. Secure. Introducing Chase Pay. #Money2020\nhttps://t.co/RBNbOFbxYY",
    "truncated": false,
    "user": {
        "contributors_enabled": false,
        "created_at": "Thu Feb 07 00:35:00 +0000 2013",
        "default_profile": false,
        "default_profile_image": false,
        "description": "Official Twitter account for the latest company news and updates from Asset Management, Private Banking, and the Corporate and Investment Bank. Learn more at:",
        "entities": {
            "description": {
                "urls": []
            },
            "url": {
                "urls": [
                    {
                        "display_url": "jpmorgan.com",
                        "expanded_url": "http://www.jpmorgan.com",
                        "indices": [
                            0,
                            22
                        ],
                        "url": "http://t.co/WJwk1XOtUh"
                    }
                ]
            }
        },
        "favourites_count": 23,
        "follow_request_sent": false,
        "followers_count": 181841,
        "following": false,
        "friends_count": 57,
        "geo_enabled": false,
        "has_extended_profile": false,
        "id": 1155522630,
        "id_str": "1155522630",
        "is_translation_enabled": false,
        "is_translator": false,
        "lang": "en",
        "listed_count": 1162,
        "location": "",
        "name": "J.P. Morgan",
        "notifications": false,
        "profile_background_color": "321B0F",
        "profile_background_image_url": "http://pbs.twimg.com/profile_background_images/378800000066830587/d0d0b1fc488eb54de172af2b9faf9c43.png",
        "profile_background_image_url_https": "https://pbs.twimg.com/profile_background_images/378800000066830587/d0d0b1fc488eb54de172af2b9faf9c43.png",
        "profile_background_tile": false,
        "profile_banner_url": "https://pbs.twimg.com/profile_banners/1155522630/1429010191",
        "profile_image_url": "http://pbs.twimg.com/profile_images/461908736106168320/S9sGEWmY_normal.png",
        "profile_image_url_https": "https://pbs.twimg.com/profile_images/461908736106168320/S9sGEWmY_normal.png",
        "profile_link_color": "4F2824",
        "profile_sidebar_border_color": "FFFFFF",
        "profile_sidebar_fill_color": "DDEEF6",
        "profile_text_color": "333333",
        "profile_use_background_image": true,
        "protected": false,
        "screen_name": "jpmorgan",
        "statuses_count": 3037,
        "time_zone": "Eastern Time (US & Canada)",
        "url": "http://t.co/WJwk1XOtUh",
        "utc_offset": -14400,
        "verified": true
    }
}