{
  "downs": 0,
  "mod_reports": [],
  "secure_media_embed": {},
  "_info_url": "https://api.reddit.com/api/info/",
  "gilded": 0,
  "num_comments": 10,
  "_orphaned": {},
  "hidden": false,
  "ups": 77,
  "url": "http://bigstory.ap.org/article/e4ff0d10af5147938a266fe872f6e7de/2-citigroup-affiliates-paying-1795m-resolve-sec-case",
  "_has_fetched": true,
  "quarantine": false,
  "name": "t3_3hcf24",
  "user_reports": [],
  "saved": false,
  "permalink": "https://www.reddit.com/r/news/comments/3hcf24/two_citigroup_inc_affiliates_have_agreed_to_pay/?ref=search_posts",
  "over_18": false,
  "is_self": false,
  "_params": {},
  "thumbnail": "",
  "created_utc": 1439836224.0,
  "_replaced_more": false,
  "subreddit_id": "t5_2qh3l",
  "archived": false,
  "domain": "bigstory.ap.org",
  "clicked": false,
  "score": 77,
  "id": "3hcf24",
  "stickied": false,
  "media_embed": {},
  "visited": false,
  "selftext": "",
  "hide_score": false,
  "_api_link": "https://api.reddit.com/r/news/comments/3hcf24/two_citigroup_inc_affiliates_have_agreed_to_pay/?ref=search_posts",
  "locked": false,
  "edited": false,
  "title": "Two Citigroup Inc. affiliates have agreed to pay $179.5 million to resolve federal regulators' charges of misleading investors in hedge funds that later collapsed",
  "created": 1439839824.0,
  "_comments_by_id": {}
}