{
    "contributors": null,
    "coordinates": null,
    "created_at": "Fri Oct 30 01:02:51 +0000 2015",
    "entities": {
        "hashtags": [],
        "symbols": [],
        "urls": [],
        "user_mentions": [
            {
                "id": 18735040,
                "id_str": "18735040",
                "indices": [
                    0,
                    10
                ],
                "name": "Bank of America Help",
                "screen_name": "BofA_Help"
            }
        ]
    },
    "favorite_count": 0,
    "favorited": false,
    "geo": null,
    "id": 659898222471548928,
    "id_str": "659898222471548928",
    "in_reply_to_screen_name": "BofA_Help",
    "in_reply_to_status_id": 659896200791990272,
    "in_reply_to_status_id_str": "659896200791990272",
    "in_reply_to_user_id": 18735040,
    "in_reply_to_user_id_str": "18735040",
    "is_quote_status": false,
    "lang": "en",
    "metadata": {
        "iso_language_code": "en",
        "result_type": "recent"
    },
    "place": {
        "attributes": {},
        "bounding_box": {
            "coordinates": [
                [
                    [
                        -90.5232883,
                        38.592875
                    ],
                    [
                        -90.432983,
                        38.592875
                    ],
                    [
                        -90.432983,
                        38.673901
                    ],
                    [
                        -90.5232883,
                        38.673901
                    ]
                ]
            ],
            "type": "Polygon"
        },
        "contained_within": [],
        "country": "United States",
        "country_code": "US",
        "full_name": "Town and Country, MO",
        "id": "88a1b7a750eeaa8d",
        "name": "Town and Country",
        "place_type": "city",
        "url": "https://api.twitter.com/1.1/geo/id/88a1b7a750eeaa8d.json"
    },
    "retweet_count": 0,
    "retweeted": false,
    "source": "<a href=\"http://twitter.com/download/iphone\" rel=\"nofollow\">Twitter for iPhone</a>",
    "text": "@BofA_Help I was finally  attended to thanks!!",
    "truncated": false,
    "user": {
        "contributors_enabled": false,
        "created_at": "Sun Mar 22 20:33:55 +0000 2015",
        "default_profile": true,
        "default_profile_image": false,
        "description": "GHANAIAN\u2757\ufe0fOLUWA MADE\u2665\u2764\ufe0f\u2764\ufe0f\u2764\ufe0f \u2197\ufe0fMaryville University",
        "entities": {
            "description": {
                "urls": []
            }
        },
        "favourites_count": 1110,
        "follow_request_sent": false,
        "followers_count": 619,
        "following": false,
        "friends_count": 352,
        "geo_enabled": true,
        "has_extended_profile": true,
        "id": 3103672488,
        "id_str": "3103672488",
        "is_translation_enabled": false,
        "is_translator": false,
        "lang": "en",
        "listed_count": 6,
        "location": "Missouri, USA",
        "name": "Azaaay",
        "notifications": false,
        "profile_background_color": "C0DEED",
        "profile_background_image_url": "http://abs.twimg.com/images/themes/theme1/bg.png",
        "profile_background_image_url_https": "https://abs.twimg.com/images/themes/theme1/bg.png",
        "profile_background_tile": false,
        "profile_banner_url": "https://pbs.twimg.com/profile_banners/3103672488/1445986936",
        "profile_image_url": "http://pbs.twimg.com/profile_images/659933398052372480/qoKUmQPW_normal.jpg",
        "profile_image_url_https": "https://pbs.twimg.com/profile_images/659933398052372480/qoKUmQPW_normal.jpg",
        "profile_link_color": "0084B4",
        "profile_sidebar_border_color": "C0DEED",
        "profile_sidebar_fill_color": "DDEEF6",
        "profile_text_color": "333333",
        "profile_use_background_image": true,
        "protected": false,
        "screen_name": "nana_gyedua",
        "statuses_count": 10016,
        "time_zone": null,
        "url": null,
        "utc_offset": null,
        "verified": false
    }
}